navaid_api/__init__.py
navaid_api/config.py
navaid_api/main.py
navaid_api/parser.py
navaid_api-1.0.0.dist-info/METADATA
navaid_api-1.0.0.dist-info/WHEEL
navaid_api-1.0.0.dist-info/entry_points.txt
navaid_api-1.0.0.dist-info/RECORD
