Metadata-Version: 2.4
Name: navaid-api
Version: 1.0.0
Summary: REST API for FAA NAVAID and fix coordinates
License-Expression: MIT
Requires-Python: >=3.10
Requires-Dist: fastapi>=0.104.0
Requires-Dist: python-dotenv>=1.0.0
Requires-Dist: uvicorn[standard]>=0.24.0
Provides-Extra: dev
Requires-Dist: pytest; extra == 'dev'
Requires-Dist: requests; extra == 'dev'
